omf/__init__.py
omf/_version.py
omf/base.py
omf/data.py
omf/fileio/__init__.py
omf/fileio/fileio.py
omf/fileio/geoh5.py
omf/fileio/utils.py
omf/lineset.py
omf/pointset.py
omf/scripts/__init__.py
omf/scripts/geoh5_to_omf.py
omf/scripts/omf_to_geoh5.py
omf/serializers.py
omf/surface.py
omf/texture.py
omf/volume.py
mira_omf-3.3.2.dist-info/METADATA
mira_omf-3.3.2.dist-info/WHEEL
mira_omf-3.3.2.dist-info/entry_points.txt
mira_omf-3.3.2.dist-info/licenses/LICENSE
mira_omf-3.3.2.dist-info/licenses/THIRD_PARTY_SOFTWARE.rst
mira_omf-3.3.2.dist-info/RECORD
