Metadata-Version: 2.4
Name: mira-omf
Version: 3.3.2
Summary: API Library for Open Mining Format
License-Expression: MIT
License-File: LICENSE
License-File: THIRD_PARTY_SOFTWARE.rst
Keywords: geology,geophysics,earth sciences
Author: Mira Geoscience
Author-email: support@mirageoscience.com
Maintainer: Dominique Fournier
Maintainer-email: dominiquef@mirageoscience.com
Requires-Python: >=3.10,<4.0
Classifier: Development Status :: 4 - Beta
Classifier: Natural Language :: English
Classifier: Operating System :: MacOS
Classifier: Operating System :: Microsoft :: Windows
Classifier: Operating System :: POSIX
Classifier: Operating System :: Unix
Classifier: Programming Language :: Python
Classifier: Programming Language :: Python :: 3
Classifier: Programming Language :: Python :: 3.10
Classifier: Programming Language :: Python :: 3.11
Classifier: Programming Language :: Python :: 3.12
Classifier: Programming Language :: Python :: 3.13
Classifier: Programming Language :: Python :: 3.14
Classifier: Topic :: Scientific/Engineering
Classifier: Topic :: Scientific/Engineering :: Mathematics
Classifier: Topic :: Scientific/Engineering :: Physics
Requires-Dist: geoh5py (>=0.12.0b5,<0.13.dev)
Requires-Dist: numpy (>=1.26.0,<1.27.0)
Requires-Dist: properties (==0.6.*)
Requires-Dist: pypng (>=0.20220715,<0.20220716)
Requires-Dist: six (>=1.16,<2.0)
Requires-Dist: vectormath (==0.2.*)
Project-URL: Homepage, https://www.mirageoscience.com/mining-industry-software/python-integration/
Project-URL: Repository, https://github.com/MiraGeoscience/omf
